extra_model/__init__.py
extra_model/_adjectives.py
extra_model/_aspects.py
extra_model/_cli.py
extra_model/_disambiguate.py
extra_model/_errors.py
extra_model/_filter.py
extra_model/_models.py
extra_model/_run.py
extra_model/_setup.py
extra_model/_summarize.py
extra_model/_topics.py
extra_model/_vectorizer.py
extra_model/py.typed
tests/__init__.py
tests/test_adjectives.py
tests/test_aspects.py
tests/test_cli.py
tests/test_disambiguate.py
tests/test_filter.py
tests/test_init.py
tests/test_models.py
tests/test_run.py
tests/test_setup.py
tests/test_summarize.py
tests/test_topics.py
tests/test_vectorizer.py
extra_model-0.4.0.dist-info/LICENSE
extra_model-0.4.0.dist-info/METADATA
extra_model-0.4.0.dist-info/WHEEL
extra_model-0.4.0.dist-info/entry_points.txt
extra_model-0.4.0.dist-info/top_level.txt
extra_model-0.4.0.dist-info/RECORD
