Metadata-Version: 2.1
Name: extra-model
Version: 0.4.0
Summary: Code to run the Extra algorithm for unsupervised topic extraction.
Home-page: https://github.com/wayfair-incubator/extra-model
Author: Misha Balyasin
Author-email: mbalyasin@wayfair.com
License: MIT License
Classifier: Development Status :: 4 - Beta
Classifier: Programming Language :: Python
Classifier: Programming Language :: Python :: 3
Classifier: Programming Language :: Python :: 3.8
Classifier: Programming Language :: Python :: 3.9
License-File: LICENSE
Requires-Dist: click (==8.1.3)
Requires-Dist: numpy (==1.23.4)
Requires-Dist: nltk (==3.7)
Requires-Dist: scikit-learn (==1.1.3)
Requires-Dist: vaderSentiment (==3.3.2)
Requires-Dist: pandas (==1.5.1)
Requires-Dist: langdetect (==1.0.9)
Requires-Dist: networkx (==2.8.7)
Requires-Dist: gensim (==4.2.0)
Requires-Dist: scipy (==1.9.3)
Requires-Dist: spacy (==3.4.2)
